dotbackup.py
dotbackup-1.2.3.data/data/share/man/man1/dotbackup.1
dotbackup-1.2.3.data/data/share/man/man1/dotsetup.1
dotbackup-1.2.3.dist-info/METADATA
dotbackup-1.2.3.dist-info/WHEEL
dotbackup-1.2.3.dist-info/entry_points.txt
dotbackup-1.2.3.dist-info/licenses/LICENSE
dotbackup-1.2.3.dist-info/RECORD
