Metadata-Version: 2.4
Name: dotbackup
Version: 1.2.3
Summary: YAML config based backup utility. Easy to use yet flexible. With a primary focus on dotfile backup & setup, but not limited to dotfiles.
Project-URL: Homepage, https://github.com/jaxvanyang/dotbackup
Project-URL: Source, https://github.com/jaxvanyang/dotbackup
Project-URL: Repository, https://github.com/jaxvanyang/dotbackup.git
Project-URL: Issues, https://github.com/jaxvanyang/dotbackup/issues
Author-email: Jax Young <jaxvanyang@gmail.com>
License-File: LICENSE
Keywords: YAML,backup,dotfiles
Classifier: Development Status :: 5 - Production/Stable
Classifier: Intended Audience :: Developers
Classifier: License :: OSI Approved :: MIT License
Classifier: Operating System :: POSIX
Classifier: Programming Language :: Python :: 3
Classifier: Programming Language :: Python :: 3 :: Only
Classifier: Programming Language :: Python :: 3.8
Classifier: Programming Language :: Python :: 3.9
Classifier: Programming Language :: Python :: 3.10
Classifier: Programming Language :: Python :: 3.11
Classifier: Programming Language :: Python :: 3.12
Classifier: Topic :: System :: Archiving :: Backup
Requires-Python: >=3.8
Requires-Dist: ruamel-yaml
